LICENSE
MANIFEST.in
README.md
pyproject.toml
requirements.txt
setup.cfg
setup.py
src/cryptoadvance/specterext/exfund/__init__.py
src/cryptoadvance/specterext/exfund/__main__.py
src/cryptoadvance/specterext/exfund/appconfig.py
src/cryptoadvance/specterext/exfund/config.py
src/cryptoadvance/specterext/exfund/controller.py
src/cryptoadvance/specterext/exfund/service.py
src/cryptoadvance/specterext/exfund/util.py
src/cryptoadvance/specterext/exfund/static/exfund/img/logo.png
src/cryptoadvance/specterext/exfund/static/exfund/img/logo.svg
src/cryptoadvance/specterext/exfund/templates/exfund/index.jinja
src/cryptoadvance/specterext/exfund/templates/exfund/table.jinja
src/cryptoadvance/specterext/exfund/templates/exfund/components/fee-selection.html
src/specterext_exfund.egg-info/PKG-INFO
src/specterext_exfund.egg-info/SOURCES.txt
src/specterext_exfund.egg-info/dependency_links.txt
src/specterext_exfund.egg-info/top_level.txt