Metadata-Version: 2.1
Name: specterext-exfund
Version: 0.1.2
Summary: Specter Desktop extension to fund multiple addresses in one go
Home-page: https://github.com/stepansnigirev/specterext-exfund
Author: Stepan Snigirev
Author-email: snigirev.stepan@gmail.com
License: UNKNOWN
Project-URL: Bug Tracker, https://github.com/stepansnigirev/specterext-exfund/issues
Platform: UNKNOWN
Classifier: Programming Language :: Python :: 3
Classifier: License :: OSI Approved :: MIT License
Classifier: Operating System :: OS Independent
Requires-Python: >=3.6
